strangeworks_hybrid_optimize/__init__.py
strangeworks_hybrid_optimize/sdk.py
strangeworks_hybrid_optimize/utils.py
strangeworks_hybrid_optimize-0.1.6.dist-info/METADATA
strangeworks_hybrid_optimize-0.1.6.dist-info/WHEEL
strangeworks_hybrid_optimize-0.1.6.dist-info/RECORD
