Metadata-Version: 2.1
Name: strangeworks-hybrid-optimize
Version: 0.1.6
Summary: Extension to strangeworks sdk to allow user to run the hybrid optimization service
Author: SFlann
Author-email: stuart@strangeworks.com
Requires-Python: >=3.10,<3.12
Classifier: Programming Language :: Python :: 3
Classifier: Programming Language :: Python :: 3.10
Classifier: Programming Language :: Python :: 3.11
Requires-Dist: dimod (>=0.12.4,<0.13.0)
Requires-Dist: networkx (>=3.0,<4.0)
Requires-Dist: numpy (==1.23.2)
Requires-Dist: qiskit (>=0.41.0,<0.42.0)
Requires-Dist: strangeworks (==0.4.4)
Requires-Dist: strangeworks-optimization-models (>=0.1.1,<0.2.0)
